Metadata-Version: 2.1
Name: jwt-eddsa-base44
Version: 0.0.1
Summary: Implementation of EdDSA JWT with base44 encoding
Home-page: https://github.com/ocordeiro/jwt-eddsa-b44
Author: ocordeiro
Author-email: alan@cordeiro.me
License: MIT
